{
  "method": "unlearn",
  "command": "train",
  "experiment_name": "train_un_si3_adapt_ph3",
  "source_train_dir": "/home/parisaat/scratch/data/cc359/siemens3/slices/train",
  "source_val_dir": "/home/parisaat/scratch/data/cc359/siemens3/slices/test",
  "target_train_dir": "/home/parisaat/scratch/data/cc359/ge3/slices/train",
  "target_val_dir": "/home/parisaat/scratch/data/cc359/ge3/slices/test",
  "batch_size": 16,
  "channels_first": true,
  "diff_model_flag": false,
  "alpha": 50,
  "patience": 25,
  "epochs": 300,
  "epoch_stage_1": 100,
  "checkpoint": 20,
  "epoch_reached": 1,
  "beta": 10,
  "log_interval": 10,
  "gpu": 0,
  "problem": "ss",
  "learning_rate": 1e-4,
  "out_dir": "out_train_un_si3_adapt_ph3"
}
